f1_2020_telemetry/__init__.py
f1_2020_telemetry/packets.py
f1_2020_telemetry/types.py
f1_2020_telemetry/cli/__init__.py
f1_2020_telemetry/cli/monitor.py
f1_2020_telemetry/cli/player.py
f1_2020_telemetry/cli/recorder.py
f1_2020_telemetry/cli/threading_utils.py
f1_2020_telemetry/gui/__init__.py
f1_2020_telemetry/gui/monitor.py
f1_2020_telemetry/tests/__init__.py
f1_2020_telemetry/tests/test_packet_event_penalty.py
f1_2020_telemetry/tests/test_packet_event_speedtrap.py
f1_2020_telemetry/tests/test_packet_header.py
f1_2020_telemetry/tests/test_packet_sizes.py
f1_2020_telemetry-0.2.1.dist-info/LICENSE
f1_2020_telemetry-0.2.1.dist-info/METADATA
f1_2020_telemetry-0.2.1.dist-info/WHEEL
f1_2020_telemetry-0.2.1.dist-info/entry_points.txt
f1_2020_telemetry-0.2.1.dist-info/top_level.txt
f1_2020_telemetry-0.2.1.dist-info/RECORD
