Metadata-Version: 2.1
Name: f1-2020-telemetry
Version: 0.2.1
Summary: A package to handle UDP telemetry data as sent by the F1 2020 game.
Home-page: https://pypi.org/project/f1-2020-telemetry/
Author: Guillaume Parent
Author-email: gp@gparent.net
License: UNKNOWN
Project-URL: Documentation, https://f1-2020-telemetry.readthedocs.io/en/latest/
Project-URL: Source Repository, https://gitlab.com/gparent/f1-2020-telemetry/
Platform: UNKNOWN
Classifier: Programming Language :: Python :: 3
Classifier: License :: OSI Approved :: MIT License
Classifier: Topic :: Games/Entertainment
Classifier: Operating System :: OS Independent
Requires-Python: >=3.6
